musamusa_textref/aboutproject.py
musamusa_textref/semisortedtextrefsdict.py
musamusa_textref/subref.py
musamusa_textref/textrefbaseclass.py
musamusa_textref/textrefdefault.py
musamusa_textref/textrefoeverses.py
musamusa_textref-0.2.2.dist-info/LICENSE
musamusa_textref-0.2.2.dist-info/WHEEL
musamusa_textref-0.2.2.dist-info/METADATA
musamusa_textref-0.2.2.dist-info/RECORD
