Metadata-Version: 2.1
Name: musamusa-textref
Version: 0.2.2
Summary: "Beowulf.4c" < "Beowulf.5a"
License: GPLv3
Author: suizokukan
Author-email: suizokukan@orange.fr
Requires-Python: >=3.9,<4.0
Classifier: License :: Other/Proprietary License
Classifier: Programming Language :: Python :: 3
Classifier: Programming Language :: Python :: 3.9
Requires-Dist: musamusa-romannumbers (>=0.1.3,<0.2.0)
